python_stingray-0.1.1.dist-info/METADATA
python_stingray-0.1.1.dist-info/RECORD
python_stingray-0.1.1.dist-info/WHEEL
python_stingray-0.1.1.dist-info/top_level.txt
stingray/__init__.py
stingray/apiclient/__init__.py
stingray/config/__init__.py
stingray/config/pools.py
stingray/config/traffic_ip_groups.py
stingray/config/virtual_servers.py
